Metadata-Version: 2.1
Name: scrapy-auto-translation-middleware
Version: 0.0.5
Summary: A Scrapy spider-middleware that performs automatic translation when the spider is working
Home-page: https://github.com/jiansongyang/scrapy-auto-translation-middleware
Author: Jiansong Yang
Author-email: yangjiansong@gmail.com
License: MIT
Platform: UNKNOWN
Classifier: Programming Language :: Python :: 3
Classifier: License :: OSI Approved :: MIT License
Classifier: Operating System :: OS Independent
Requires-Python: >=3.6
